ed_domain_model/__init__.py
ed_domain_model/entities/__init__.py
ed_domain_model/entities/bill.py
ed_domain_model/entities/business.py
ed_domain_model/entities/car.py
ed_domain_model/entities/consumer.py
ed_domain_model/entities/delivery_job.py
ed_domain_model/entities/driver.py
ed_domain_model/entities/driver_payment.py
ed_domain_model/entities/location.py
ed_domain_model/entities/notification.py
ed_domain_model/entities/order.py
ed_domain_model/entities/otp.py
ed_domain_model/entities/route.py
ed_domain_model/entities/user.py
ed_domain_model/entities/warehouse_worker.py
ed_domain_model/queues/__init__.py
ed_domain_model/queues/notification/__init__.py
ed_domain_model/queues/notification/notification_model.py
ed_domain_model/queues/order/__init__.py
ed_domain_model/queues/order/business_model.py
ed_domain_model/queues/order/consumer_model.py
ed_domain_model/queues/order/order_model.py
ed_domain_model/services/__init__.py
ed_domain_model/services/auth/__init__.py
ed_domain_model/services/auth/auth_endpoints.py
ed_domain_model/services/auth/dtos/__init__.py
ed_domain_model/services/auth/dtos/create_user_dto.py
ed_domain_model/services/auth/dtos/create_user_verify_dto.py
ed_domain_model/services/auth/dtos/login_user_dto.py
ed_domain_model/services/auth/dtos/login_user_verify_dto.py
ed_domain_model/services/auth/dtos/unverified_user_dto.py
ed_domain_model/services/auth/dtos/user_dto.py
ed_domain_model/services/auth/dtos/verify_token_dto.py
ed_domain_model/services/common/__init__.py
ed_domain_model/services/common/endpoint.py
ed_domain_model/services/common/generic_responce.py
ed_domain_model/services/common/http_methods.py
ed_domain_model/services/core/__init__.py
ed_domain_model/services/core/core_endpoints.py
ed_domain_model/services/core/dtos/__init__.py
ed_domain_model/services/core/dtos/business_dto.py
ed_domain_model/services/core/dtos/car_dto.py
ed_domain_model/services/core/dtos/consumer_dto.py
ed_domain_model/services/core/dtos/create_business_dto.py
ed_domain_model-0.1.9.dist-info/LICENSE
ed_domain_model-0.1.9.dist-info/METADATA
ed_domain_model-0.1.9.dist-info/WHEEL
ed_domain_model-0.1.9.dist-info/top_level.txt
ed_domain_model-0.1.9.dist-info/RECORD
